pernum2string/__init__.py
pernum2string/pernum2string.py
pernum2string-0.0.9.dist-info/LICENSE
pernum2string-0.0.9.dist-info/METADATA
pernum2string-0.0.9.dist-info/WHEEL
pernum2string-0.0.9.dist-info/top_level.txt
pernum2string-0.0.9.dist-info/RECORD
