Metadata-Version: 2.1
Name: pernum2string
Version: 0.0.9
Summary: this module convert number persian word
Home-page: https://github.com/pypa/sampleproject
Author: mahsa homayooniya
Author-email: homayooniya@gmail.com
License: 'MIT'
Project-URL: Bug Tracker, https://github.com/pypa/sampleproject/issues
Platform: UNKNOWN
Classifier: Programming Language :: Python :: 3
Classifier: License :: OSI Approved :: MIT License
Classifier: Operating System :: OS Independent
Requires-Python: >=3.6
License-File: LICENSE
